enum_compat.py
pycaption/__init__.py
pycaption/base.py
pycaption/english.pickle
pycaption/exceptions.py
pycaption/geometry.py
pycaption/sami.py
pycaption/srt.py
pycaption/transcript.py
pycaption/utils.py
pycaption/webvtt.py
pycaption/dfxp/__init__.py
pycaption/dfxp/base.py
pycaption/dfxp/extras.py
pycaption/scc/__init__.py
pycaption/scc/constants.py
pycaption/scc/specialized_collections.py
pycaption/scc/state_machines.py
tests/__init__.py
tests/mixins.py
tests/test_base.py
tests/test_dfxp.py
tests/test_dfxp_conversion.py
tests/test_dfxp_extras.py
tests/test_ensure_valid_input.py
tests/test_functions.py
tests/test_geometry.py
tests/test_sami.py
tests/test_sami_conversion.py
tests/test_scc.py
tests/test_scc_conversion.py
tests/test_srt.py
tests/test_srt_conversion.py
tests/test_webvtt.py
tests/test_webvtt_conversion.py
tests/samples/__init__.py
tests/samples/dfxp.py
tests/samples/sami.py
tests/samples/scc.py
tests/samples/srt.py
tests/samples/webvtt.py
le_pycaption-2.2.0a1.dist-info/LICENSE.txt
le_pycaption-2.2.0a1.dist-info/METADATA
le_pycaption-2.2.0a1.dist-info/WHEEL
le_pycaption-2.2.0a1.dist-info/top_level.txt
le_pycaption-2.2.0a1.dist-info/RECORD
