Metadata-Version: 2.1
Name: le-pycaption
Version: 2.2.0a1
Summary: Closed caption converter
Home-page: https://github.com/learningequality/pycaption
Author: Joe Norton <joey@nortoncrew.com>
Author-email: blaine@learningequality.org
License: Apache License, Version 2.0
Platform: UNKNOWN
Classifier: Development Status :: 3 - Alpha
Classifier: License :: OSI Approved :: Apache Software License
Classifier: Programming Language :: Python :: 2.7
Classifier: Programming Language :: Python :: 3.5
Classifier: Programming Language :: Python :: 3.6
Classifier: Programming Language :: Python :: 3.7
Classifier: Topic :: Multimedia :: Video
Requires-Dist: beautifulsoup4 (<4.9.0,>=4.6.3)
Requires-Dist: lxml (>=3.2.3)
Requires-Dist: cssutils (>=0.9.10)
Requires-Dist: future
Requires-Dist: six (>=1.9.0)
